{"normalized_a_hrefs": ["mailto:fmoore@smu.edu", "http://lyle.smu.edu", "http://lyle.smu.edu/~fmoore/index-fall2017.htm", "https://s2.smu.edu/~fmoore/schedule.htm", "https://s2.smu.edu/~fmoore/CSE5337_syllabus.pdf", "https://s2.smu.edu/~fmoore/CSE7337_syllabus.pdf"], "requested_url": "https://s2.smu.edu/~fmoore/index.htm", "normalized_img_srcs": ["https://s2.smu.edu/~fmoore/SMU-CSE-LOGO-COLOR.gif"], "resolved_normalized_img_srcs": ["https://s2.smu.edu/~fmoore/SMU-CSE-LOGO-COLOR.gif"], "content_type": "text/html", "resolved_requested_url": "https://s2.smu.edu/~fmoore/index.htm", "resolved_normalized_a_hrefs": ["mailto:fmoore@smu.edu", "https://www.smu.edu/lyle", "https://s2.smu.edu/~fmoore/index-fall2017.htm", "https://s2.smu.edu/~fmoore/schedule.htm", "https://s2.smu.edu/~fmoore/CSE5337_syllabus.pdf", "https://s2.smu.edu/~fmoore/CSE7337_syllabus.pdf"], "redirect_history": [], "content_hash": "d4d64dbb697ca67d7251c08f93fbe576", "url_id": 16, "status_code": 200}